{"uid": "1357-D3", "url": "https://codeforces.com/contest/1357/problem/D3", "tags": [], "title": "1357-D3", "statement": "D3. Quantum Classification - Dataset 5time limit per test2 secondsmemory limit per test256 megabytesinputstandard inputoutputstandard outputThis problem is identical to the problemD1in every aspect except thetraining dataset. Please refer to that problem for the full problem statement.", "source": "CF", "vjudge": false, "processed": [{"prompt_md5": "8b78ef4a", "template_md5": "35d339e4", "result": "You are given a dataset with features and labels. Your task is to build a model that can accurately predict the labels for new, unseen data points based on their features.  The performance of your model will be evaluated based on its accuracy. \n\n\nLet me know if you'd like help understanding any specific part of this or need further clarification!"}, {"prompt_md5": "72392fc3", "template_md5": "465699a0", "result": "You are given a dataset and need to build a model that can classify data points into categories."}]}